hdrpy/__init__.py
hdrpy-0.3.3.dist-info/DESCRIPTION.rst
hdrpy-0.3.3.dist-info/METADATA
hdrpy-0.3.3.dist-info/RECORD
hdrpy-0.3.3.dist-info/WHEEL
hdrpy-0.3.3.dist-info/metadata.json
hdrpy-0.3.3.dist-info/pbr.json
hdrpy-0.3.3.dist-info/top_level.txt
