Metadata-Version: 1.1
Name: hdrpy
Version: 0.3.3
Summary: HDR histogram implementation based on numpy
Home-page: https://github.com/dmand/hdrpy
Author: Dmitri Pribysh
Author-email: dmand@yandex.ru
License: Apache 2.0
Keywords: hdrpy,hdr,histogram,high dynamic range
Platform: UNKNOWN
Classifier: Intended Audience :: Developers
Classifier: Intended Audience :: Information Technology
Classifier: Intended Audience :: System Administrators
Classifier: License :: OSI Approved :: Apache Software License
Classifier: Operating System :: POSIX :: Linux
Classifier: Operating System :: MacOS
Classifier: Operating System :: Microsoft :: Windows
Classifier: Programming Language :: Python
Classifier: Programming Language :: Python :: 2
Classifier: Programming Language :: Python :: 2.7
Classifier: Programming Language :: Python :: 3
